aihandler/__init__.py
aihandler/base_runner.py
aihandler/controlnet_utils.py
aihandler/database.py
aihandler/llmrunner.py
aihandler/logger.py
aihandler/offline_client.py
aihandler/pyqt_offline_client.py
aihandler/qtvar.py
aihandler/runner.py
aihandler/settings.py
aihandler/settings_manager.py
aihandler/socket_server.py
aihandlerwindows-1.8.19.dist-info/LICENSE
aihandlerwindows-1.8.19.dist-info/METADATA
aihandlerwindows-1.8.19.dist-info/WHEEL
aihandlerwindows-1.8.19.dist-info/top_level.txt
aihandlerwindows-1.8.19.dist-info/RECORD
