Metadata-Version: 2.1
Name: aihandlerwindows
Version: 1.8.19
Summary: AI Handler: An engine which wraps certain huggingface models
Home-page: https://github.com/Capsize-Games/aihandler/tree/develop-windows
Author: Capsize LLC
Author-email: contact@capsize.gg
License: AGPL-3.0
Keywords: ai,chatbot,chat,ai
Requires-Python: >=3.10.0
License-File: LICENSE
Requires-Dist: omegaconf
Requires-Dist: lightning (==1.9.0)
Requires-Dist: accelerate (==0.18.0)
Requires-Dist: controlnet-aux
Requires-Dist: huggingface-hub (==0.13.3)
Requires-Dist: numpy (==1.23.5)
Requires-Dist: Pillow (==9.4.0)
Requires-Dist: pip (==23.0.1)
Requires-Dist: PyQt6 (==6.4.2)
Requires-Dist: PyQt6-Qt6 (==6.4.3)
Requires-Dist: PyQt6-sip (==13.4.1)
Requires-Dist: pyqtdarktheme (==2.1.0)
Requires-Dist: pyre-extensions (==0.0.23)
Requires-Dist: pytorch-lightning (==2.0.0)
Requires-Dist: requests (==2.28.2)
Requires-Dist: requests-oauthlib (==1.3.1)
Requires-Dist: safetensors (==0.3.0)
Requires-Dist: scipy (==1.10.1)
Requires-Dist: tensorflow (==2.12.0)
Requires-Dist: tokenizers (==0.13.2)
Requires-Dist: tqdm (==4.65.0)
Requires-Dist: xformers (==0.0.16)
Requires-Dist: charset-normalizer (==3.1.0)
Requires-Dist: opencv-python (==4.7.0.72)
Requires-Dist: setuptools (==65.5.1)
Requires-Dist: sympy (==1.11.1)
Requires-Dist: typing-extensions (==4.5.0)
Requires-Dist: urllib3 (==1.26.15)
